{
  "formatVersion": "1",
  "header": {
    "description": "Maintain Error Code KVB",
    "originalLanguage": "en",
    "abapLanguageVersion": "cloudDevelopment"
  },
  "serviceConfiguration": {
    "serviceBinding": "ZUI_ERRORCODEKVB_O4",
    "serviceName": "ZUI_ERRORCODEKVB_O4",
    "serviceVersion": "0001",
    "rootEntitySet": "ErrorCodeKvbAll",
    "name": "Error Code KVB",
    "configurationGroup": "",
    "skipRootEntity": true
  },
  "appConfiguration": {
    "listReport": {},
    "objectPages": [
      {
        "entitySet": "ErrorCodeKvbAll",
        "variantManagement": "control"
      }
    ],
    "tableSettings": [
      {
        "entitySet": "ErrorCodeKvb",
        "tableType": "gridTable",
        "selectionMode": "auto",
        "rowCountMode": "auto",
        "frozenColumnCount": 1,
        "creationModeName": "inlineCreationRows",
        "createAtEnd": true,
        "widthIncludingColumnHeader": true
      }
    ]
  }
}
